LICENSE.txt
Makefile
README.txt
TODO.txt
setup.py
etc/collective.facetednavigation-configure.zcml
src/collective/__init__.py
src/collective.facetednavigation.egg-info/PKG-INFO
src/collective.facetednavigation.egg-info/SOURCES.txt
src/collective.facetednavigation.egg-info/dependency_links.txt
src/collective.facetednavigation.egg-info/namespace_packages.txt
src/collective.facetednavigation.egg-info/not-zip-safe
src/collective.facetednavigation.egg-info/top_level.txt
src/collective/facetednavigation/CHANGES.txt
src/collective/facetednavigation/LICENSE.txt
src/collective/facetednavigation/README.txt
src/collective/facetednavigation/VERSION.txt
src/collective/facetednavigation/__init__.py
src/collective/facetednavigation/configure.zcml
src/collective/facetednavigation/exportimport.py
src/collective/facetednavigation/tool.py
src/collective/facetednavigation/browser/__init__.py
src/collective/facetednavigation/browser/batch.py
src/collective/facetednavigation/browser/configure.zcml
src/collective/facetednavigation/browser/facetednavigation.py
src/collective/facetednavigation/browser/utils.py
src/collective/facetednavigation/browser/resources/facetednavigation.css
src/collective/facetednavigation/browser/resources/facetednavigation.kss
src/collective/facetednavigation/browser/templates/facetednavigation.pt
src/collective/facetednavigation/browser/templates/facetednavigation_macros.pt
src/collective/facetednavigation/doc/install.txt
src/collective/facetednavigation/locales/README.txt
src/collective/facetednavigation/locales/collective.facetednavigation-plone.pot
src/collective/facetednavigation/locales/collective.facetednavigation.pot
src/collective/facetednavigation/locales/compile.sh
src/collective/facetednavigation/locales/es/LC_MESSAGES/collective.facetednavigation-plone-es.mo
src/collective/facetednavigation/locales/es/LC_MESSAGES/collective.facetednavigation-plone-es.po
src/collective/facetednavigation/locales/es/LC_MESSAGES/collective.facetednavigation.mo
src/collective/facetednavigation/locales/es/LC_MESSAGES/collective.facetednavigation.po
src/collective/facetednavigation/locales/fr/LC_MESSAGES/collective.facetednavigation.mo
src/collective/facetednavigation/locales/fr/LC_MESSAGES/collective.facetednavigation.po
src/collective/facetednavigation/profiles/default/actions.xml
