Metadata-Version: 1.0
Name: collective.facetednavigation
Version: 0.7.1
Summary: Collective Faceted Navigation provides an user interface which lets an user browse items of a Plone site by selecting amongst pre-defined criteria.
Home-page: http://plone.org/products/faceted-navigation
Author: Damien Baty
Author-email: damien.baty@removethis.gmail.com
License: GNU GPL
Download-URL: http://cheeseshop.python.org/pypi/collective.facetednavigation
Keywords: Plone facet faceted navigation user interface
Platform: UNKNOWN
Classifier: Development Status :: 4 - Beta
Classifier: Environment :: Web Environment
Classifier: Framework :: Plone
Classifier: Intended Audience :: Developers
Classifier: Intended Audience :: End Users/Desktop
Classifier: Intended Audience :: Information Technology
Classifier: License :: OSI Approved :: GNU General Public License (GPL)
Classifier: Natural Language :: English
Classifier: Natural Language :: French
Classifier: Operating System :: OS Independent
Classifier: Programming Language :: Python
